ifrc_go_py/__init__.py
ifrc_go_py/module.py
ifrc_go_py-0.1.3.dist-info/METADATA
ifrc_go_py-0.1.3.dist-info/WHEEL
ifrc_go_py-0.1.3.dist-info/top_level.txt
ifrc_go_py-0.1.3.dist-info/RECORD
