Metadata-Version: 2.1
Name: ifrc-go-py
Version: 0.1.3
Summary: A library for working with IFRC GO data.
Home-page: UNKNOWN
Author: Jonathan Garro
Author-email: jonathan.garro@gmail.com
License: MIT
Project-URL: GitHub, https://github.com/JonathanGarro/go-py
Platform: UNKNOWN
Requires-Dist: requests (>=2.0.0)
Requires-Dist: seaborn (==0.12.2)
Requires-Dist: matplotlib (==3.7.2)
Requires-Dist: geopandas (==0.13.2)
Requires-Dist: pandas (>=1.5.0)
